easy_insight/__init__.py
easy_insight/eda_tools/__init__.py
easy_insight/eda_tools/basic_data_inspection.py
easy_insight/eda_tools/bivariate_analysis.py
easy_insight/eda_tools/missing_values_analysis.py
easy_insight/eda_tools/multivariate_analysis.py
easy_insight/eda_tools/univariate_analysis.py
easy_insight/eda_tools/utility.py
easy_insight-1.0.4.dist-info/LICENSE
easy_insight-1.0.4.dist-info/METADATA
easy_insight-1.0.4.dist-info/WHEEL
easy_insight-1.0.4.dist-info/RECORD
