Metadata-Version: 2.1
Name: easy-insight
Version: 1.0.4
Summary: A simple library for easy exploratory data analysis
Home-page: https://github.com/DurgeshRathod/easy-insight
Keywords: exploratory-data-analysis,eda,data analysis,machine learning,visualisations
Author: Durgesh Rathod
Author-email: durgeshrathod.777@gmail.com
Requires-Python: >=3.10,<4.0
Classifier: Programming Language :: Python :: 3
Classifier: Programming Language :: Python :: 3.10
Classifier: Programming Language :: Python :: 3.11
Classifier: Programming Language :: Python :: 3.12
Classifier: Programming Language :: Python :: 3.13
Requires-Dist: matplotlib (>=3.9.2,<4.0.0)
Requires-Dist: numpy (>=2.1.2,<3.0.0)
Requires-Dist: pandas (>=2.2.3,<3.0.0)
Requires-Dist: seaborn (>=0.13.2,<0.14.0)
Requires-Dist: setuptools (>=75.3.0,<76.0.0)
Project-URL: Repository, https://github.com/DurgeshRathod/easy-insight
